{
  "variants": {
    "facing=north,left=false": { "model": "jsblock:block/exit_sign_1e_right" },
    "facing=east,left=false": { "model": "jsblock:block/exit_sign_1e_right", "y": 90 },
    "facing=west,left=false": { "model": "jsblock:block/exit_sign_1e_right", "y": 270 },
    "facing=south,left=false": { "model": "jsblock:block/exit_sign_1e_right", "y": 180 },
    "facing=north,left=true": { "model": "jsblock:block/exit_sign_1e_left" },
    "facing=east,left=true": { "model": "jsblock:block/exit_sign_1e_left", "y": 90 },
    "facing=west,left=true": { "model": "jsblock:block/exit_sign_1e_left", "y": 270 },
    "facing=south,left=true": { "model": "jsblock:block/exit_sign_1e_left", "y": 180 }
  }
}